erodius-0.0.1.dist-info/RECORD
erodius-0.0.1.dist-info/WHEEL
erodius-0.0.1.dist-info/METADATA
erodius/__init__.pyi
erodius/__init__.py
erodius/_core.cpython-311-darwin.so
